NeSST/__init__.py
NeSST/collisions.py
NeSST/constants.py
NeSST/core.py
NeSST/cross_sections.py
NeSST/endf_interface.py
NeSST/fitting.py
NeSST/spectral_model.py
NeSST/time_of_flight.py
NeSST/utils.py
NeSST/data/Be9.json
NeSST/data/C12.json
NeSST/data/H1.json
NeSST/data/H2.json
NeSST/data/H3.json
NeSST/data/TT_reac_ENDF.dat
NeSST/data/TT_reac_Hale.dat
NeSST/data/TT_reac_McNally.dat
NeSST/data/TT_spec_temprange.txt
NeSST/data/VerbinskiLproton.csv
NeSST/data/__init__.py
NeSST/data/ENDF/n-001_H_001.endf
NeSST/data/ENDF/n-001_H_002.cendl
NeSST/data/ENDF/n-001_H_002.endf
NeSST/data/ENDF/n-001_H_003.brond
NeSST/data/ENDF/n-001_H_003.endf
NeSST/data/ENDF/n-004_Be_009.endf
NeSST/data/ENDF/n-006_C_012.endf
nesst-1.1.2.dist-info/licenses/LICENSE
nesst-1.1.2.dist-info/METADATA
nesst-1.1.2.dist-info/WHEEL
nesst-1.1.2.dist-info/top_level.txt
nesst-1.1.2.dist-info/RECORD
