Metadata-Version: 2.4
Name: NeSST
Version: 1.1.2
Summary: Neutron Scattered Spectra Tool, ICF primary and scattered neutron spectroscopy analysis code
Author: Aidan Crilly <ac116@ic.ac.uk>
Project-URL: Homepage, https://github.com/aidancrilly/NeSST
Project-URL: Bug Tracker, https://github.com/aidancrilly/NeSST/issues
Keywords: python,reactor,fusion,power,sankey
Classifier: Programming Language :: Python :: 3
Classifier: License :: OSI Approved :: MIT License
Classifier: Operating System :: OS Independent
Classifier: Intended Audience :: Science/Research
Requires-Python: >=3.0
License-File: LICENSE
Requires-Dist: numpy
Requires-Dist: scipy
Requires-Dist: matplotlib
Requires-Dist: endf
Provides-Extra: test
Requires-Dist: pre-commit; extra == "test"
Requires-Dist: pytest; extra == "test"
Requires-Dist: jupyter; extra == "test"
Requires-Dist: matplotlib; extra == "test"
Dynamic: license-file
